pydddi/__init__.py
pydddi/application/usecase.py
pydddi/domain/entity.py
pydddi/domain/model.py
pydddi/domain/service.py
pydddi/infrastructure/repository.py
pydantic_ddd_interface-0.2.0.dist-info/LICENSE
pydantic_ddd_interface-0.2.0.dist-info/METADATA
pydantic_ddd_interface-0.2.0.dist-info/WHEEL
pydantic_ddd_interface-0.2.0.dist-info/RECORD
