Metadata-Version: 2.3
Name: pydantic_ddd_interface
Version: 0.2.0
Summary: A Python library providing interface definitions for Domain-Driven Design (DDD) patterns using Pydantic for type safety and validation.
License: MIT
Keywords: ddd,domain-driven-design,pydantic,architecture,interface
Author: nodashin
Author-email: nodashin.jpn@gmail.com
Requires-Python: >=3.12
Classifier: Development Status :: 3 - Alpha
Classifier: Intended Audience :: Developers
Classifier: License :: OSI Approved :: MIT License
Classifier: Programming Language :: Python :: 3
Classifier: Programming Language :: Python :: 3.12
Classifier: Programming Language :: Python :: 3.13
Classifier: Topic :: Software Development :: Libraries :: Python Modules
Requires-Dist: pydantic (>=2.11.5,<3.0.0)
